gigacommit/__init__.py
gigacommit/gigacommit
gigacommit-0.1.1.data/scripts/gigacommit
gigacommit-0.1.1.dist-info/LICENSE
gigacommit-0.1.1.dist-info/METADATA
gigacommit-0.1.1.dist-info/WHEEL
gigacommit-0.1.1.dist-info/top_level.txt
gigacommit-0.1.1.dist-info/RECORD
